{
  "first_room": {
    "name": "Nexus",
    "desc": "The First Room",
    "sealed": {
      "inbound": false,
      "outbound": false
    }
  },
  "first_user": {
    "nick": "Root User",
    "desc": "The first user and administrator.",
    "autolook": {
      "enabled": true
    },
    "chat": {
      "enabled": true
    },
    "builder": {
      "enabled": true
    },
    "cecho": {
      "enabled": true
    },
    "colors": {
      "enabled": false
    },
    "lang": "common"
  },
  "items": {
    "glued": false,
    "hidden": false,
    "truehide": false,
    "chance": 1,
    "container": {
      "enabled": false      
    }
  },
  "rooms": {
    "sealed": {
      "inbound": false,
      "outbound": false
    }
  },
  "users": {
    "autolook": {
      "enabled": true
    },
    "chat": {
      "enabled": true
    },
    "builder": {
      "enabled": true
    },
    "cecho": {
      "enabled": true
    },
    "colors": {
      "enabled": false
    },
    "lang": "common"
  },
  "help": {
    "columns": 6
  }
}
